LICENSE
MANIFEST.in
README.md
pyproject.toml
requirements.txt
setup.cfg
setup.py
vtarget/__init__.py
vtarget.egg-info/PKG-INFO
vtarget.egg-info/SOURCES.txt
vtarget.egg-info/dependency_links.txt
vtarget.egg-info/requires.txt
vtarget.egg-info/top_level.txt
vtarget/dataprep/__init__.py
vtarget/dataprep/builder.py
vtarget/dataprep/pipeline.py
vtarget/dataprep/types.py
vtarget/dataprep/nodes/api_rest.py
vtarget/dataprep/nodes/chain_exec.py
vtarget/dataprep/nodes/code.py
vtarget/dataprep/nodes/column.py
vtarget/dataprep/nodes/concat.py
vtarget/dataprep/nodes/concat_multi.py
vtarget/dataprep/nodes/cross_join.py
vtarget/dataprep/nodes/cumsum.py
vtarget/dataprep/nodes/cut.py
vtarget/dataprep/nodes/data_cleansing.py
vtarget/dataprep/nodes/database.py
vtarget/dataprep/nodes/database_write.py
vtarget/dataprep/nodes/datetime_extract.py
vtarget/dataprep/nodes/datetime_fill.py
vtarget/dataprep/nodes/datetime_formatter.py
vtarget/dataprep/nodes/datetime_range.py
vtarget/dataprep/nodes/dbscan.py
vtarget/dataprep/nodes/describe.py
vtarget/dataprep/nodes/df_maker.py
vtarget/dataprep/nodes/drop_duplicates.py
vtarget/dataprep/nodes/dtype.py
vtarget/dataprep/nodes/email.py
vtarget/dataprep/nodes/excel.py
vtarget/dataprep/nodes/filter.py
vtarget/dataprep/nodes/formula.py
vtarget/dataprep/nodes/get_file.py
vtarget/dataprep/nodes/get_web.py
vtarget/dataprep/nodes/groupby.py
vtarget/dataprep/nodes/input_data.py
vtarget/dataprep/nodes/inter_row.py
vtarget/dataprep/nodes/isin.py
vtarget/dataprep/nodes/keep_col.py
vtarget/dataprep/nodes/kmeans.py
vtarget/dataprep/nodes/louvain.py
vtarget/dataprep/nodes/melt.py
vtarget/dataprep/nodes/merge.py
vtarget/dataprep/nodes/output.py
vtarget/dataprep/nodes/pivot.py
vtarget/dataprep/nodes/quality.py
vtarget/dataprep/nodes/regex.py
vtarget/dataprep/nodes/replace.py
vtarget/dataprep/nodes/rolling.py
vtarget/dataprep/nodes/sample.py
vtarget/dataprep/nodes/shape.py
vtarget/dataprep/nodes/sort.py
vtarget/dataprep/nodes/split.py
vtarget/dataprep/nodes/switch.py
vtarget/dataprep/nodes/unique.py
vtarget/dataprep/nodes/v_output.py
vtarget/dataprep/nodes/value_counts.py
vtarget/handlers/automl_cache.py
